simplecipher/__init__.py
simplecipher/simplecipher.py
simplecipher-0.2.2.dist-info/LICENSE
simplecipher-0.2.2.dist-info/METADATA
simplecipher-0.2.2.dist-info/WHEEL
simplecipher-0.2.2.dist-info/top_level.txt
simplecipher-0.2.2.dist-info/RECORD
