Metadata-Version: 2.1
Name: simplecipher
Version: 0.2.2
Summary: A simple cipher
Home-page: https://github.com/nightowlish/simplecipher
Author: nightowlish
Author-email: oanaolf@gmail.com
License: UNKNOWN
Platform: UNKNOWN
Classifier: Programming Language :: Python :: 3
Classifier: License :: OSI Approved :: Apache Software License
Classifier: Operating System :: OS Independent
Requires-Python: >=3.6
License-File: LICENSE
